term_ascii_diagram/__init__.py
term_ascii_diagram/core.py
term_ascii_diagram/diagram.py
term_ascii_diagram/main.py
term_ascii_diagram/status_bar.py
term_ascii_diagram-0.0.5.dist-info/METADATA
term_ascii_diagram-0.0.5.dist-info/WHEEL
term_ascii_diagram-0.0.5.dist-info/entry_points.txt
term_ascii_diagram-0.0.5.dist-info/licenses/LICENSE
term_ascii_diagram-0.0.5.dist-info/RECORD
