Metadata-Version: 2.3
Name: term-ascii-diagram
Version: 0.0.5
Summary: Build ASCII diagrams in terminal using keyboard.
Project-URL: Homepage, https://github.com/amirkarimi/term-ascii-diagram
Project-URL: Issues, https://github.com/amirkarimi/term-ascii-diagram/issues
Author-email: Amir Karimi <me@amirkarimi.dev>
License-File: LICENSE
Classifier: License :: OSI Approved :: MIT License
Classifier: Operating System :: POSIX
Classifier: Programming Language :: Python :: 3
Classifier: Topic :: Terminals
Classifier: Topic :: Utilities
Requires-Python: >=3.8
